mercado/__init__.py
mercado/cli.py
mercado/tool_manager.py
mercado/tools.py
mercado/utils.py
mercado/vendors/__init__.py
mercado/vendors/github.py
mercado/vendors/hashicorp.py
mercado/vendors/shell.py
mercado/vendors/url_fetcher.py
mercado/vendors/vendor.py
mercado-0.2.1.dist-info/entry_points.txt
mercado-0.2.1.dist-info/WHEEL
mercado-0.2.1.dist-info/METADATA
mercado-0.2.1.dist-info/RECORD
