Metadata-Version: 2.1
Name: mercado
Version: 0.2.1
Summary: All-In-One Development CLI Tools Multi-platform Marketplace
Home-page: https://github.com/YuviGold/mercado
Keywords: cli,devops,automation
Author: YuviGold
Requires-Python: >=3.10,<4.0
Classifier: Programming Language :: Python :: 3
Classifier: Programming Language :: Python :: 3.10
Classifier: Programming Language :: Python :: 3.11
Requires-Dist: humanize (>=4.4.0,<5.0.0)
Requires-Dist: requests (>=2.28.1,<3.0.0)
Requires-Dist: rich (>=12.6,<14.0)
Requires-Dist: typer (>=0.6.1,<0.10.0)
Project-URL: Repository, https://github.com/YuviGold/mercado
